environment_parser/__init__.py
environment_parser/environment.py
environment_parser/parse.py
environment_parser/sources.py
environment_parser-0.0.1.dist-info/METADATA
environment_parser-0.0.1.dist-info/WHEEL
environment_parser-0.0.1.dist-info/top_level.txt
environment_parser-0.0.1.dist-info/RECORD
