Metadata-Version: 2.1
Name: environment-parser
Version: 0.0.1
Summary: Lightweight library to parse environment variables from shell, stdin or .env file in python.
Home-page: https://github.com/sledeunf/environment-parser
Author: Sylvan Le Deunff
Author-email: sledeunf@gmail.com
License: UNKNOWN
Platform: UNKNOWN
Classifier: Programming Language :: Python :: 3
Classifier: License :: OSI Approved :: MIT License
Classifier: Operating System :: OS Independent
Requires-Python: >=3.6
